classicML/__init__.py
classicML/api/__init__.py
classicML/api/models/__init__.py
classicML/api/models/base_model.py
classicML/api/models/bayes/__init__.py
classicML/api/models/bayes/naive_bayes_classifier.py
classicML/api/models/bayes/semi_naive_bayes_classifiers.py
classicML/api/models/cluster/__init__.py
classicML/api/models/cluster/k_means.py
classicML/api/models/ensemble/__init__.py
classicML/api/models/ensemble/bagging.py
classicML/api/models/ensemble/base_learners.py
classicML/api/models/ensemble/boosting.py
classicML/api/models/linear_model/__init__.py
classicML/api/models/linear_model/linear_discriminant_analysis.py
classicML/api/models/linear_model/logistic_regression.py
classicML/api/models/neural_network/__init__.py
classicML/api/models/neural_network/back_propagation_neural_network.py
classicML/api/models/neural_network/radial_basis_function_network.py
classicML/api/models/support_vector_machine/__init__.py
classicML/api/models/support_vector_machine/support_vector_classifier.py
classicML/api/models/tree/__init__.py
classicML/api/models/tree/decision_tree_classifier.py
classicML/api/plots/__init__.py
classicML/api/plots/bayes.py
classicML/api/plots/callbacks.py
classicML/api/plots/cluster.py
classicML/api/plots/ensemble.py
classicML/api/plots/linear_model.py
classicML/api/plots/support_vector_machine.py
classicML/api/plots/tree.py
classicML/api/plots/utils.py
classicML/backend/__init__.py
classicML/backend/io.py
classicML/backend/training.py
classicML/backend/python/__init__.py
classicML/backend/python/_utils.py
classicML/backend/python/activations.py
classicML/backend/python/callbacks.py
classicML/backend/python/initializers.py
classicML/backend/python/kernels.py
classicML/backend/python/losses.py
classicML/backend/python/metrics.py
classicML/backend/python/ops.py
classicML/backend/python/optimizers.py
classicML/backend/python/data/__init__.py
classicML/backend/python/data/dataset.py
classicML/backend/python/data/preprocessing.py
classicML_python-0.9.dist-info/LICENSE
classicML_python-0.9.dist-info/METADATA
classicML_python-0.9.dist-info/WHEEL
classicML_python-0.9.dist-info/top_level.txt
classicML_python-0.9.dist-info/RECORD
