Metadata-Version: 2.1
Name: classicML-python
Version: 0.9
Summary: An easy-to-use ML framework
Home-page: https://github.com/sun1638650145/classicML
Author: Steve R. Sun
Author-email: s1638650145@gmail.com
License: Apache Software License
Platform: UNKNOWN
Classifier: Development Status :: 5 - Production/Stable
Classifier: License :: OSI Approved :: Apache Software License
Classifier: Operating System :: OS Independent
Classifier: Programming Language :: Python :: 3
Classifier: Programming Language :: Python :: 3.7
Classifier: Programming Language :: Python :: 3.8
Classifier: Programming Language :: Python :: 3.9
Classifier: Programming Language :: Python :: 3.10
Classifier: Topic :: Scientific/Engineering :: Artificial Intelligence
Requires-Python: >=3.7
License-File: LICENSE
Requires-Dist: h5py (<=3.7.0,>=3.7.0)
Requires-Dist: matplotlib (<=3.5.2,>=3.5.0)
Requires-Dist: numpy (<=1.22.4,>=1.21.0)
Requires-Dist: packaging (<=21.3,>=21.3)
Requires-Dist: pandas (<=1.4.2,>=1.3.4)
Requires-Dist: psutil (<=5.9.1,>=5.7.2)
